[
  {
    "Name": "string",
    "StepName": "string",
    "StartDelayMS": "int",
    "EndDelayMS": "int",
    "ForceSpeechBubbleCloseMS": "int",
    "StartCondition": "string",
    "StartLocationX": "int",
    "StartLocationY": "int",
    "StartLocationRadius": "int",
    "AnimationX": "int",
    "AnimationY": "int",
    "AnimationX2": "int",
    "AnimationY2": "int",
    "CompleteCondition": "string",
    "ShouldUseAutoShoot": "boolean",
    "CompleteLocationX": "int",
    "CompleteLocationY": "int",
    "CompleteLocationRadius": "int",
    "UseUltiX": "int",
    "UseUltiY": "int",
    "AnimationClipSWF": "string",
    "AnimationMovieClip": "string",
    "AnimationClipSWF2": "string",
    "AnimationMovieClip2": "string",
    "SpeechBubbleCharacterSWF": "string",
    "SpeechBubbleCharacterMovieClip": "string",
    "SpeechBubbleTIDs": "string",
    "StartSound": "string",
    "SpawnCharacter": "string",
    "SpawnLocationX": "int",
    "SpawnLocationY": "int",
    "CustomData": "int",
    "BlockingSpeechBubble": "boolean",
    "ShowUlti": "boolean",
    "ShowShootStick": "boolean",
    "LeftSpeechBubble": "boolean"
  }
]
